tests/__init__.py
tests/test.py
torchpm/__init__.py
torchpm/covariate.py
torchpm/data.py
torchpm/linearode.py
torchpm/loss.py
torchpm/misc.py
torchpm/models.py
torchpm/parameter.py
torchpm/predfunction.py
torchpm-0.0.7.dist-info/LICENSE
torchpm-0.0.7.dist-info/METADATA
torchpm-0.0.7.dist-info/WHEEL
torchpm-0.0.7.dist-info/top_level.txt
torchpm-0.0.7.dist-info/RECORD
